daycolor/__init__.py
daycolor/daycolor.py
daycolor-0.0.1.dist-info/METADATA
daycolor-0.0.1.dist-info/RECORD
daycolor-0.0.1.dist-info/WHEEL
daycolor-0.0.1.dist-info/top_level.txt
