Metadata-Version: 2.1
Name: daycolor
Version: 0.0.1
Summary: Return a interpolated RGB color depending on the time of the day
Home-page: https://github.com/atoav/daycolor
Author: David Huss
Author-email: dh@atoav.com
License: UNKNOWN
Platform: UNKNOWN
Classifier: Programming Language :: Python :: 3
Classifier: License :: OSI Approved :: MIT License
Classifier: Operating System :: OS Independent
